{
    "target_url": "https://www.binance.com/en-GB/trade?type=cross",
    "domains": {
        "accounts.binance.com": [
            "https://accounts.binance.com/en-GB/login?loginChannel=&return_to=aHR0cHM6Ly93d3cuYmluYW5jZS5jb20vZW4tR0IvdHJhZGU%2FdHlwZT1jcm9zcw%3D%3D",
            "https://accounts.binance.com/en-GB/register?registerChannel=&return_to=aHR0cHM6Ly93d3cuYmluYW5jZS5jb20vZW4tR0IvdHJhZGU%2FdHlwZT1jcm9zcw%3D%3D"
        ],
        "launchpad.binance.com": [
            "https://launchpad.binance.com/en-GB"
        ],
        "p2p.binance.com": [
            "https://p2p.binance.com/en-GB/trade/all-payments/USDT?fiat=GBP"
        ],
        "www.binance.com": [
            "https://www.binance.com/en-GB/",
            "https://www.binance.com/en-GB/auto-invest/",
            "https://www.binance.com/en-GB/chat",
            "https://www.binance.com/en-GB/convert",
            "https://www.binance.com/en-GB/crypto/buy/GBP/BTC",
            "https://www.binance.com/en-GB/earn",
            "https://www.binance.com/en-GB/fan-token",
            "https://www.binance.com/en-GB/fee/trading",
            "https://www.binance.com/en-GB/markets/spot_margin-FIAT",
            "https://www.binance.com/en-GB/nft/home",
            "https://www.binance.com/en-GB/orderbook/BTC_USDT",
            "https://www.binance.com/en-GB/support",
            "https://www.binance.com/en-GB/support/announcement/360031505011",
            "https://www.binance.com/en-GB/support/faq/18c97e8ab67a4e1b824edd590cae9f16",
            "https://www.binance.com/en-GB/trade-rule",
            "https://www.binance.com/en-GB/trade?type=cross",
            "https://www.binance.com/en-GB/trading-bots"
        ]
    }
}