{
    "target_url": "https://bitcoin.org/zh_CN/protect-your-privacy",
    "domains": {
        "": [
            "bitcoin:bc1qx3u4njquj0ux63030r4nat8awqrlm0x2zlt96h"
        ],
        "bitcoin.org": [
            "https://bitcoin.org/ar/protect-your-privacy",
            "https://bitcoin.org/bg/protect-your-privacy",
            "https://bitcoin.org/ca/protegeix-la-teva-privacitat",
            "https://bitcoin.org/da/beskyt-dit-privatliv",
            "https://bitcoin.org/de/schuetzen-sie-ihre-privatsphaere",
            "https://bitcoin.org/el/protect-your-privacy",
            "https://bitcoin.org/en/alerts",
            "https://bitcoin.org/en/blog",
            "https://bitcoin.org/en/privacy",
            "https://bitcoin.org/en/protect-your-privacy",
            "https://bitcoin.org/es/proteja-su-privacidad",
            "https://bitcoin.org/fa/protect-your-privacy",
            "https://bitcoin.org/fr/proteger-votre-vie-privee",
            "https://bitcoin.org/he/protect-your-privacy",
            "https://bitcoin.org/hi/protect-your-privacy",
            "https://bitcoin.org/hu/vedje-meg-szemelyes-adatait",
            "https://bitcoin.org/hy/protect-your-privacy",
            "https://bitcoin.org/id/lindungi-privasi-anda",
            "https://bitcoin.org/it/proteggi-la-tua-privacy",
            "https://bitcoin.org/ja/protect-your-privacy",
            "https://bitcoin.org/km/protect-your-privacy",
            "https://bitcoin.org/ko/protect-your-privacy",
            "https://bitcoin.org/nl/bescherm-uw-privacy",
            "https://bitcoin.org/pl/chron-swoja-prywatnosc",
            "https://bitcoin.org/pt_BR/proteger-sua-privacidade",
            "https://bitcoin.org/ro/protejeaza-ti-intimitatea",
            "https://bitcoin.org/ru/protect-your-privacy",
            "https://bitcoin.org/sl/zascita-zasebnosti",
            "https://bitcoin.org/sr/zastitite-svoju-privatnost",
            "https://bitcoin.org/sv/skydda-din-integritet",
            "https://bitcoin.org/tr/gizliliginizi-koruyun",
            "https://bitcoin.org/uk/protect-your-privacy",
            "https://bitcoin.org/zh_CN/",
            "https://bitcoin.org/zh_CN/about-us",
            "https://bitcoin.org/zh_CN/bitcoin-for-businesses",
            "https://bitcoin.org/zh_CN/bitcoin-for-individuals",
            "https://bitcoin.org/zh_CN/bitcoin-paper",
            "https://bitcoin.org/zh_CN/buy",
            "https://bitcoin.org/zh_CN/community",
            "https://bitcoin.org/zh_CN/development",
            "https://bitcoin.org/zh_CN/download",
            "https://bitcoin.org/zh_CN/events",
            "https://bitcoin.org/zh_CN/exchanges",
            "https://bitcoin.org/zh_CN/faq",
            "https://bitcoin.org/zh_CN/getting-started",
            "https://bitcoin.org/zh_CN/how-it-works",
            "https://bitcoin.org/zh_CN/innovation",
            "https://bitcoin.org/zh_CN/legal",
            "https://bitcoin.org/zh_CN/press",
            "https://bitcoin.org/zh_CN/protect-your-privacy",
            "https://bitcoin.org/zh_CN/protect-your-privacy#future",
            "https://bitcoin.org/zh_CN/protect-your-privacy#iplog",
            "https://bitcoin.org/zh_CN/protect-your-privacy#mixing",
            "https://bitcoin.org/zh_CN/protect-your-privacy#public",
            "https://bitcoin.org/zh_CN/protect-your-privacy#receive",
            "https://bitcoin.org/zh_CN/protect-your-privacy#traceable",
            "https://bitcoin.org/zh_CN/resources",
            "https://bitcoin.org/zh_CN/support-bitcoin",
            "https://bitcoin.org/zh_CN/vocabulary",
            "https://bitcoin.org/zh_CN/you-need-to-know",
            "https://bitcoin.org/zh_TW/protect-your-privacy"
        ],
        "developer.bitcoin.org": [
            "https://developer.bitcoin.org/"
        ],
        "opensource.org": [
            "http://opensource.org/licenses/mit-license.php"
        ],
        "www.torproject.org": [
            "https://www.torproject.org/"
        ]
    }
}