{
    "target_url": "https://bitcoin.org/en/scams",
    "domains": {
        "": [
            "bitcoin:bc1qx3u4njquj0ux63030r4nat8awqrlm0x2zlt96h"
        ],
        "bitcoin.org": [
            "https://bitcoin.org/ar/",
            "https://bitcoin.org/bg/",
            "https://bitcoin.org/ca/estafes",
            "https://bitcoin.org/da/",
            "https://bitcoin.org/de/scams",
            "https://bitcoin.org/el/",
            "https://bitcoin.org/en/",
            "https://bitcoin.org/en/about-us",
            "https://bitcoin.org/en/alerts",
            "https://bitcoin.org/en/bitcoin-core/",
            "https://bitcoin.org/en/bitcoin-for-businesses",
            "https://bitcoin.org/en/bitcoin-for-individuals",
            "https://bitcoin.org/en/bitcoin-paper",
            "https://bitcoin.org/en/blog",
            "https://bitcoin.org/en/buy",
            "https://bitcoin.org/en/community",
            "https://bitcoin.org/en/development",
            "https://bitcoin.org/en/events",
            "https://bitcoin.org/en/exchanges",
            "https://bitcoin.org/en/faq",
            "https://bitcoin.org/en/full-node",
            "https://bitcoin.org/en/getting-started",
            "https://bitcoin.org/en/how-it-works",
            "https://bitcoin.org/en/innovation",
            "https://bitcoin.org/en/legal",
            "https://bitcoin.org/en/press",
            "https://bitcoin.org/en/privacy",
            "https://bitcoin.org/en/resources",
            "https://bitcoin.org/en/scams",
            "https://bitcoin.org/en/scams#blackmail",
            "https://bitcoin.org/en/scams#fake-exchanges",
            "https://bitcoin.org/en/scams#free-giveaways",
            "https://bitcoin.org/en/scams#impersonation",
            "https://bitcoin.org/en/scams#malware",
            "https://bitcoin.org/en/scams#meet-in-person",
            "https://bitcoin.org/en/scams#money-transfer-fraud",
            "https://bitcoin.org/en/scams#phishing-emails",
            "https://bitcoin.org/en/scams#phishing-websites",
            "https://bitcoin.org/en/scams#ponzi-schemes",
            "https://bitcoin.org/en/scams#prize-giveaways",
            "https://bitcoin.org/en/scams#pump-and-dumps",
            "https://bitcoin.org/en/scams#pyramid-schemes",
            "https://bitcoin.org/en/scams#ransomware",
            "https://bitcoin.org/en/scams#scam-coins",
            "https://bitcoin.org/en/support-bitcoin",
            "https://bitcoin.org/en/vocabulary",
            "https://bitcoin.org/en/you-need-to-know",
            "https://bitcoin.org/es/",
            "https://bitcoin.org/fa/",
            "https://bitcoin.org/fr/",
            "https://bitcoin.org/he/",
            "https://bitcoin.org/hi/",
            "https://bitcoin.org/hu/atveresek",
            "https://bitcoin.org/hy/scams",
            "https://bitcoin.org/id/scam",
            "https://bitcoin.org/it/truffe",
            "https://bitcoin.org/ja/scams",
            "https://bitcoin.org/km/scams",
            "https://bitcoin.org/ko/",
            "https://bitcoin.org/nl/oplichtingspraktijken",
            "https://bitcoin.org/pl/",
            "https://bitcoin.org/pt_BR/fraudes",
            "https://bitcoin.org/ro/",
            "https://bitcoin.org/ru/",
            "https://bitcoin.org/sl/",
            "https://bitcoin.org/sr/prevare",
            "https://bitcoin.org/sv/bedragerier",
            "https://bitcoin.org/tr/",
            "https://bitcoin.org/uk/",
            "https://bitcoin.org/zh_CN/",
            "https://bitcoin.org/zh_TW/"
        ],
        "developer.bitcoin.org": [
            "https://developer.bitcoin.org/"
        ],
        "opensource.org": [
            "http://opensource.org/licenses/mit-license.php"
        ]
    }
}