{
    "target_url": "https://ethereum.org/en/roadmap/dencun/",
    "domains": {
        "": [
            "mailto:press@ethereum.org"
        ],
        "blog.ethereum.org": [
            "https://blog.ethereum.org/",
            "https://blog.ethereum.org/2024/02/27/dencun-mainnet-announcement",
            "https://blog.ethereum.org/2024/02/27/dencun-mainnet-announcement#client-releases"
        ],
        "devcon.org": [
            "https://devcon.org/"
        ],
        "discord.gg": [
            "https://discord.gg/ethereum-org"
        ],
        "eips.ethereum.org": [
            "https://eips.ethereum.org/EIPS/eip-4844"
        ],
        "esp.ethereum.foundation": [
            "https://esp.ethereum.foundation"
        ],
        "ethereum.org": [
            "https://ethereum.org/en/",
            "https://ethereum.org/en/about/",
            "https://ethereum.org/en/about/#open-jobs",
            "https://ethereum.org/en/assets/",
            "https://ethereum.org/en/bug-bounty/",
            "https://ethereum.org/en/community/",
            "https://ethereum.org/en/community/code-of-conduct/",
            "https://ethereum.org/en/community/events/",
            "https://ethereum.org/en/community/grants/",
            "https://ethereum.org/en/community/online/",
            "https://ethereum.org/en/community/research/",
            "https://ethereum.org/en/contributing/",
            "https://ethereum.org/en/contributing/translation-program/",
            "https://ethereum.org/en/cookie-policy/",
            "https://ethereum.org/en/dao/",
            "https://ethereum.org/en/dapps/",
            "https://ethereum.org/en/decentralized-identity/",
            "https://ethereum.org/en/defi/",
            "https://ethereum.org/en/developers/",
            "https://ethereum.org/en/developers/docs/",
            "https://ethereum.org/en/developers/docs/consensus-mechanisms/pos/#how-does-validation-work",
            "https://ethereum.org/en/developers/docs/design-and-ux/",
            "https://ethereum.org/en/developers/docs/intro-to-ethereum/",
            "https://ethereum.org/en/developers/docs/networking-layer/portal-network/",
            "https://ethereum.org/en/developers/learning-tools/",
            "https://ethereum.org/en/developers/local-environment/",
            "https://ethereum.org/en/developers/tutorials/",
            "https://ethereum.org/en/eips/",
            "https://ethereum.org/en/enterprise/",
            "https://ethereum.org/en/enterprise/private-ethereum/",
            "https://ethereum.org/en/eth/",
            "https://ethereum.org/en/foundation/",
            "https://ethereum.org/en/gas/",
            "https://ethereum.org/en/get-eth/",
            "https://ethereum.org/en/glossary/",
            "https://ethereum.org/en/glossary/#committee",
            "https://ethereum.org/en/glossary/#finality",
            "https://ethereum.org/en/glossary/#slot",
            "https://ethereum.org/en/governance/",
            "https://ethereum.org/en/guides/",
            "https://ethereum.org/en/history/",
            "https://ethereum.org/en/layer-2/",
            "https://ethereum.org/en/learn/",
            "https://ethereum.org/en/nft/",
            "https://ethereum.org/en/privacy-policy/",
            "https://ethereum.org/en/quizzes/",
            "https://ethereum.org/en/roadmap/",
            "https://ethereum.org/en/roadmap/danksharding/",
            "https://ethereum.org/en/roadmap/dencun/",
            "https://ethereum.org/en/roadmap/dencun/#alt-l1-fee-impact",
            "https://ethereum.org/en/roadmap/dencun/#calldata-vs-blobs",
            "https://ethereum.org/en/roadmap/dencun/#client-impact",
            "https://ethereum.org/en/roadmap/dencun/#further-reading",
            "https://ethereum.org/en/roadmap/dencun/#historical-access",
            "https://ethereum.org/en/roadmap/dencun/#l1-fee-impact",
            "https://ethereum.org/en/roadmap/dencun/#main-content",
            "https://ethereum.org/en/roadmap/dencun/#network-impact",
            "https://ethereum.org/en/roadmap/dencun/#roadmap-impact",
            "https://ethereum.org/en/roadmap/dencun/#scam-alert",
            "https://ethereum.org/en/roadmap/dencun/#testnet-impact",
            "https://ethereum.org/en/roadmap/dencun/#visual-learner",
            "https://ethereum.org/en/roadmap/dencun/#when",
            "https://ethereum.org/en/roadmap/scaling/",
            "https://ethereum.org/en/roadmap/security/",
            "https://ethereum.org/en/run-a-node/",
            "https://ethereum.org/en/security/",
            "https://ethereum.org/en/smart-contracts/",
            "https://ethereum.org/en/stablecoins/",
            "https://ethereum.org/en/staking/",
            "https://ethereum.org/en/terms-of-use/",
            "https://ethereum.org/en/wallets/",
            "https://ethereum.org/en/wallets/find-wallet/",
            "https://ethereum.org/en/web3/",
            "https://ethereum.org/en/what-is-ethereum/",
            "https://ethereum.org/en/whitepaper/"
        ],
        "github.com": [
            "https://github.com/ethereum/ethereum-org-website",
            "https://github.com/ethereum/ethereum-org-website/tree/dev/public/content/roadmap/dencun/index.md"
        ],
        "medium.com": [
            "https://medium.com/@ebunker.io/an-in-depth-explanation-of-eip-4844-the-core-of-the-cancun-upgrade-de7b13761d2c"
        ],
        "members.delphidigital.io": [
            "https://members.delphidigital.io/reports/the-hitchhikers-guide-to-ethereum/#proto-danksharding-eip-4844"
        ],
        "notes.ethereum.org": [
            "https://notes.ethereum.org/@vbuterin/proto_danksharding_faq"
        ],
        "tim.mirror.xyz": [
            "https://tim.mirror.xyz/HzH5MpK1dnw7qhBSmzCfdCIxpwpD6DpwlfxtaAwEFro"
        ],
        "twitter.com": [
            "https://twitter.com/ethdotorg"
        ],
        "www.eip4844.com": [
            "https://www.eip4844.com/"
        ]
    }
}