{
    "target_url": "https://www.binance.com/blog/launchpad/changing-the-game-binance-launchpool-announces-more-fan-tokens-to-come-421499824684901407?lang=en",
    "domains": {
        "academy.binance.com": [
            "https://academy.binance.com/ar",
            "https://academy.binance.com/ar/learn-and-earn"
        ],
        "accounts.binance.com": [
            "https://accounts.binance.com/ar/login?loginChannel=blog&return_to=aHR0cHM6Ly93d3cuYmluYW5jZS5jb20vYXIvYmxvZy9sYXVuY2hwYWQvY2hhbmdpbmctdGhlLWdhbWUtYmluYW5jZS1sYXVuY2hwb29sLWFubm91bmNlcy1tb3JlLWZhbi10b2tlbnMtdG8tY29tZS00MjE0OTk4MjQ2ODQ5MDE0MDc%2FbGFuZz1lbg%3D%3D",
            "https://accounts.binance.com/ar/register?registerChannel=blog&return_to=aHR0cHM6Ly93d3cuYmluYW5jZS5jb20vYXIvYmxvZy9sYXVuY2hwYWQvY2hhbmdpbmctdGhlLWdhbWUtYmluYW5jZS1sYXVuY2hwb29sLWFubm91bmNlcy1tb3JlLWZhbi10b2tlbnMtdG8tY29tZS00MjE0OTk4MjQ2ODQ5MDE0MDc%2FbGFuZz1lbg%3D%3D"
        ],
        "c2c.binance.com": [
            "https://c2c.binance.com/ar/merchantApplication"
        ],
        "coinmarketcap.com": [
            "https://coinmarketcap.com/exchanges/binance/"
        ],
        "discord.gg": [
            "https://discord.gg/jE4wt8g2H2"
        ],
        "labs.binance.com": [
            "https://labs.binance.com/"
        ],
        "launchpad.binance.com": [
            "https://launchpad.binance.com/ar"
        ],
        "p2p.binance.com": [
            "https://p2p.binance.com/ar",
            "https://p2p.binance.com/ar/p2pro"
        ],
        "pool.binance.com": [
            "https://pool.binance.com/ar"
        ],
        "research.binance.com": [
            "https://research.binance.com/en/projects/asr-fan-token",
            "https://research.binance.com/en/projects/atm-fan-token",
            "https://research.binance.com/en/projects/juventus-fan-token",
            "https://research.binance.com/en/projects/og-fan-token",
            "https://research.binance.com/en/projects/paris-saint-germain-fan-token"
        ],
        "twitter.com": [
            "https://twitter.com/BinanceArabic"
        ],
        "www.binance.charity": [
            "https://www.binance.charity"
        ],
        "www.binance.com": [
            "https://www.binance.com/ar/",
            "https://www.binance.com/ar/BABT?source=footer",
            "https://www.binance.com/ar/about",
            "https://www.binance.com/ar/activity/affiliate",
            "https://www.binance.com/ar/activity/referral?utm_source=Lite_web_footer",
            "https://www.binance.com/ar/airdrop",
            "https://www.binance.com/ar/altcoins/tradable",
            "https://www.binance.com/ar/binance-api",
            "https://www.binance.com/ar/blog",
            "https://www.binance.com/ar/bnb",
            "https://www.binance.com/ar/buy-sell-crypto",
            "https://www.binance.com/ar/careers",
            "https://www.binance.com/ar/chat?sourceEntry=4",
            "https://www.binance.com/ar/community",
            "https://www.binance.com/ar/convert/BNB/USDT",
            "https://www.binance.com/ar/copy-trading",
            "https://www.binance.com/ar/country-region-selector",
            "https://www.binance.com/ar/crypto/buy",
            "https://www.binance.com/ar/delivery",
            "https://www.binance.com/ar/desktop-download",
            "https://www.binance.com/ar/download",
            "https://www.binance.com/ar/download?utm_source=&utm_campaign=",
            "https://www.binance.com/ar/earn",
            "https://www.binance.com/ar/eoptions",
            "https://www.binance.com/ar/fan-token",
            "https://www.binance.com/ar/fee/schedule",
            "https://www.binance.com/ar/futures",
            "https://www.binance.com/ar/gift-card",
            "https://www.binance.com/ar/how-to-buy/bitcoin",
            "https://www.binance.com/ar/how-to-buy/bnb",
            "https://www.binance.com/ar/how-to-buy/dogecoin",
            "https://www.binance.com/ar/how-to-buy/ethereum",
            "https://www.binance.com/ar/how-to-buy/xrp",
            "https://www.binance.com/ar/land/building_trust",
            "https://www.binance.com/ar/landing/data",
            "https://www.binance.com/ar/legal/home",
            "https://www.binance.com/ar/leveraged-tokens/tokens/allTokens",
            "https://www.binance.com/ar/live",
            "https://www.binance.com/ar/loan",
            "https://www.binance.com/ar/markets/overview",
            "https://www.binance.com/ar/megadrop",
            "https://www.binance.com/ar/my/coin-apply",
            "https://www.binance.com/ar/my/user-support/feedback/entry",
            "https://www.binance.com/ar/my/wallet/account/payment",
            "https://www.binance.com/ar/nft/home",
            "https://www.binance.com/ar/official-verification",
            "https://www.binance.com/ar/otc",
            "https://www.binance.com/ar/press",
            "https://www.binance.com/ar/price",
            "https://www.binance.com/ar/price-prediction",
            "https://www.binance.com/ar/price-prediction/bitcoin",
            "https://www.binance.com/ar/price-prediction/ethereum",
            "https://www.binance.com/ar/price/bitcoin",
            "https://www.binance.com/ar/price/ethereum",
            "https://www.binance.com/ar/privacy",
            "https://www.binance.com/ar/proof-of-reserves",
            "https://www.binance.com/ar/research",
            "https://www.binance.com/ar/risk-warning",
            "https://www.binance.com/ar/square",
            "https://www.binance.com/ar/square/news/all",
            "https://www.binance.com/ar/support",
            "https://www.binance.com/ar/support/announcement",
            "https://www.binance.com/ar/support/law-enforcement",
            "https://www.binance.com/ar/support/list/notices",
            "https://www.binance.com/ar/tax",
            "https://www.binance.com/ar/terms",
            "https://www.binance.com/ar/trade",
            "https://www.binance.com/ar/trade-rule",
            "https://www.binance.com/ar/trade/BTC_USDT?type=spot",
            "https://www.binance.com/ar/trade?type=cross",
            "https://www.binance.com/ar/trading-bots",
            "https://www.binance.com/ar/vip-institutional-services",
            "https://www.binance.com/ar/web3wallet",
            "https://www.binance.com/blog",
            "https://www.binance.com/en/blog/421499824684900950/Everything-You-Need-to-Know-About-Binance-Launchpool-How-to-Farm-Tokens-Calculate-APY--More",
            "https://www.binance.com/en/blog/421499824684901014/Binance-Innovation-Zone--Listing-Updates"
        ],
        "www.bnbchain.org": [
            "https://www.bnbchain.org"
        ],
        "www.chiliz.com": [
            "https://www.chiliz.com/en/home/"
        ],
        "www.facebook.com": [
            "https://www.facebook.com/BinanceMENA"
        ],
        "www.instagram.com": [
            "https://www.instagram.com/binancemena/"
        ],
        "www.reddit.com": [
            "https://www.reddit.com/r/binance"
        ],
        "www.socios.com": [
            "https://www.socios.com/"
        ],
        "www.tiktok.com": [
            "https://www.tiktok.com/@binance?lang=en"
        ],
        "www.youtube.com": [
            "https://www.youtube.com/binanceyoutube"
        ]
    }
}