{
    "target_url": "https://support.ledger.com/hc/en-us/categories/4404376139409?docs=true",
    "domains": {
        "": [
            "mailto:media@ledger.com"
        ],
        "developers.ledger.com": [
            "https://developers.ledger.com/"
        ],
        "enterprise.ledger.com": [
            "https://enterprise.ledger.com/"
        ],
        "origin.ledger.com": [
            "https://origin.ledger.com/"
        ],
        "shop.ledger.com": [
            "https://shop.ledger.com/",
            "https://shop.ledger.com/#category__accessories",
            "https://shop.ledger.com/#category__bundle",
            "https://shop.ledger.com/pages/cookie-policy",
            "https://shop.ledger.com/pages/hardware-wallets-comparison",
            "https://shop.ledger.com/pages/ledger-live-terms-of-use",
            "https://shop.ledger.com/pages/ledger-nano-x",
            "https://shop.ledger.com/pages/other",
            "https://shop.ledger.com/pages/privacy-policy",
            "https://shop.ledger.com/pages/terms-and-conditions",
            "https://shop.ledger.com/pages/website-terms-of-use",
            "https://shop.ledger.com/products/ledger-nano-s"
        ],
        "status.ledger.com": [
            "https://status.ledger.com/"
        ],
        "support.ledger.com": [
            "https://support.ledger.com/hc/articles/15158192560157",
            "https://support.ledger.com/hc/categories/4404369571601?support=true",
            "https://support.ledger.com/hc/categories/4404376139409?docs=true",
            "https://support.ledger.com/hc/change_language/ar?return_to=%2Fhc%2Far%2Fcategories%2F4404376139409-%25D8%25A7%25D9%2584%25D8%25AA%25D9%2588%25D8%25AB%25D9%258A%25D9%2582%3Fdocs%3Dtrue",
            "https://support.ledger.com/hc/change_language/de?return_to=%2Fhc%2Fde%2Fcategories%2F4404376139409-Dokumentation%3Fdocs%3Dtrue",
            "https://support.ledger.com/hc/change_language/es?return_to=%2Fhc%2Fes%2Fcategories%2F4404376139409-Documentaci%25C3%25B3n%3Fdocs%3Dtrue",
            "https://support.ledger.com/hc/change_language/fr-fr?return_to=%2Fhc%2Ffr-fr%2Fcategories%2F4404376139409-Documentation%3Fdocs%3Dtrue",
            "https://support.ledger.com/hc/change_language/ja?return_to=%2Fhc%2Fja%2Fcategories%2F4404376139409-%25E3%2583%2589%25E3%2582%25AD%25E3%2583%25A5%25E3%2583%25A1%25E3%2583%25B3%25E3%2583%2588%3Fdocs%3Dtrue",
            "https://support.ledger.com/hc/change_language/ko?return_to=%2Fhc%2Fko%2Fcategories%2F4404376139409-%25EB%25AC%25B8%25EC%2584%259C%3Fdocs%3Dtrue",
            "https://support.ledger.com/hc/change_language/pt-br?return_to=%2Fhc%2Fpt-br%2Fcategories%2F4404376139409-Documenta%25C3%25A7%25C3%25A3o%3Fdocs%3Dtrue",
            "https://support.ledger.com/hc/change_language/ru?return_to=%2Fhc%2Fru%2Fcategories%2F4404376139409-%25D0%2594%25D0%25BE%25D0%25BA%25D1%2583%25D0%25BC%25D0%25B5%25D0%25BD%25D1%2582%25D0%25B0%25D1%2586%25D0%25B8%25D1%258F%3Fdocs%3Dtrue",
            "https://support.ledger.com/hc/change_language/tr?return_to=%2Fhc%2Ftr%2Fcategories%2F4404376139409-Belgeler%3Fdocs%3Dtrue",
            "https://support.ledger.com/hc/change_language/zh-cn?return_to=%2Fhc%2Fzh-cn%2Fcategories%2F4404376139409-%25E6%2596%2587%25E6%25A1%25A3%3Fdocs%3Dtrue",
            "https://support.ledger.com/hc/en-us",
            "https://support.ledger.com/hc/en-us/categories/4404369571601-Support?support=true",
            "https://support.ledger.com/hc/en-us/categories/4404376139409?docs=true",
            "https://support.ledger.com/hc/en-us/sections/4404369606801-Getting-Started",
            "https://support.ledger.com/hc/en-us/sections/4404369617169-Ledger-Nano-X",
            "https://support.ledger.com/hc/en-us/sections/4404369622289-Other-products",
            "https://support.ledger.com/hc/en-us/sections/4404369631249-Ledger-Live",
            "https://support.ledger.com/hc/en-us/sections/4404369637521-Crypto-assets",
            "https://support.ledger.com/hc/en-us/sections/4416934580369-Ledger-Nano-S-Plus",
            "https://support.ledger.com/hc/en-us/sections/7866669444765-Ledger-Stax",
            "https://support.ledger.com/hc/en-us/sections/9568013167773-Ledger-Recover-provided-by-Coincover"
        ],
        "www.facebook.com": [
            "https://www.facebook.com/Ledger/"
        ],
        "www.instagram.com": [
            "https://www.instagram.com/ledger/"
        ],
        "www.ledger.com": [
            "https://www.ledger.com/",
            "https://www.ledger.com/academy",
            "https://www.ledger.com/bitcoin-cash-wallet",
            "https://www.ledger.com/bitcoin-wallet",
            "https://www.ledger.com/bounty-program",
            "https://www.ledger.com/buy-bitcoin",
            "https://www.ledger.com/category/blog-posts",
            "https://www.ledger.com/coin/price",
            "https://www.ledger.com/eos-wallet",
            "https://www.ledger.com/ethereum-wallet",
            "https://www.ledger.com/in-the-news",
            "https://www.ledger.com/join-us",
            "https://www.ledger.com/ledger-live",
            "https://www.ledger.com/ledger-wallets-and-services",
            "https://www.ledger.com/partners",
            "https://www.ledger.com/phishing-campaigns-status",
            "https://www.ledger.com/reseller",
            "https://www.ledger.com/ripple-wallet",
            "https://www.ledger.com/start",
            "https://www.ledger.com/stellar-wallet",
            "https://www.ledger.com/supported-crypto-assets",
            "https://www.ledger.com/the-company",
            "https://www.ledger.com/the-people-behind-ledger",
            "https://www.ledger.com/we-are-ledger"
        ],
        "www.ledgerwallet.com": [
            "https://www.ledgerwallet.com/affiliates/"
        ],
        "www.linkedin.com": [
            "https://www.linkedin.com/company/ledgerhq/"
        ],
        "www.reddit.com": [
            "https://www.reddit.com/r/ledgerwallet/"
        ],
        "www.twitter.com": [
            "https://www.twitter.com/Ledger"
        ],
        "www.youtube.com": [
            "https://www.youtube.com/Ledger"
        ]
    }
}